safitty/__init__.py
safitty/__version__.py
safitty/core.py
safitty/dict.py
safitty/parser.py
safitty/types.py
safitty-1.3.dist-info/LICENSE
safitty-1.3.dist-info/METADATA
safitty-1.3.dist-info/WHEEL
safitty-1.3.dist-info/top_level.txt
safitty-1.3.dist-info/RECORD
