Metadata-Version: 2.1
Name: safitty
Version: 1.3
Summary: Safitty. Wrapper on JSON/YAML configs for Python.
Home-page: https://github.com/TezRomacH/safitty
Author: Roman Tezikov
Author-email: tez.romach@gmail.com
License: MIT
Platform: UNKNOWN
Classifier: License :: OSI Approved :: MIT License
Classifier: Intended Audience :: Developers
Classifier: Intended Audience :: Science/Research
Classifier: Programming Language :: Python
Classifier: Programming Language :: Python :: 3.6
Classifier: Programming Language :: Python :: 3.7
Requires-Python: >=3.6.0
Requires-Dist: PyYAML
